{
	"route"			: "errors",
	"name"			: "Errors",
	"description"	: "Component to manage Errors on Dashboard Application",
	"category"      : "ecom",
	"sub_category"  : "dashboard",
	"version"		: "0.0.1",
	"repo"			: "https://.../ecom-dashboard-component-errors",
	"class"			: "Applications\\Ecom\\Dashboard\\Components\\Errors\\ErrorsComponent",
	"dependencies"	: {
		"core"			: {
			"name"		: "Core",
			"version"	: "0.0.1",
			"repo"		: "https://.../core"
		},
		"components"	: [],
		"packages"		: [],
		"middlewares"	: [],
		"views"			: []
	},
	"menu"				: false,
	"settings"		: {
	}
}