{"267":{"category":{"categoryId":"267","categoryName":"Books, Magazines"},"categoryTreeNodeLevel":1,"childCategoryTreeNodes":[{"category":{"categoryId":"63","categoryName":"Comic Books"},"categoryTreeNodeLevel":2,"leafCategoryTreeNode":true,"parentCategoryTreeNodeHref":"https:\/\/api.sandbox.ebay.com\/commerce\/taxonomy\/v1\/category_tree\/15\/get_category_subtree?category_id=267"},{"category":{"categoryId":"268","categoryName":"Other Books"},"categoryTreeNodeLevel":2,"leafCategoryTreeNode":true,"parentCategoryTreeNodeHref":"https:\/\/api.sandbox.ebay.com\/commerce\/taxonomy\/v1\/category_tree\/15\/get_category_subtree?category_id=267"},{"category":{"categoryId":"2228","categoryName":"Textbooks"},"categoryTreeNodeLevel":2,"leafCategoryTreeNode":true,"parentCategoryTreeNodeHref":"https:\/\/api.sandbox.ebay.com\/commerce\/taxonomy\/v1\/category_tree\/15\/get_category_subtree?category_id=267"},{"category":{"categoryId":"8575","categoryName":"Manga"},"categoryTreeNodeLevel":2,"leafCategoryTreeNode":true,"parentCategoryTreeNodeHref":"https:\/\/api.sandbox.ebay.com\/commerce\/taxonomy\/v1\/category_tree\/15\/get_category_subtree?category_id=267"},{"category":{"categoryId":"11104","categoryName":"Cook Books"},"categoryTreeNodeLevel":2,"leafCategoryTreeNode":true,"parentCategoryTreeNodeHref":"https:\/\/api.sandbox.ebay.com\/commerce\/taxonomy\/v1\/category_tree\/15\/get_category_subtree?category_id=267"},{"category":{"categoryId":"16135","categoryName":"Annuals"},"categoryTreeNodeLevel":2,"leafCategoryTreeNode":true,"parentCategoryTreeNodeHref":"https:\/\/api.sandbox.ebay.com\/commerce\/taxonomy\/v1\/category_tree\/15\/get_category_subtree?category_id=267"},{"category":{"categoryId":"29223","categoryName":"Antiquarian & Collectable"},"categoryTreeNodeLevel":2,"leafCategoryTreeNode":true,"parentCategoryTreeNodeHref":"https:\/\/api.sandbox.ebay.com\/commerce\/taxonomy\/v1\/category_tree\/15\/get_category_subtree?category_id=267"},{"category":{"categoryId":"29399","categoryName":"Wholesale Lots"},"categoryTreeNodeLevel":2,"leafCategoryTreeNode":true,"parentCategoryTreeNodeHref":"https:\/\/api.sandbox.ebay.com\/commerce\/taxonomy\/v1\/category_tree\/15\/get_category_subtree?category_id=267"},{"category":{"categoryId":"29792","categoryName":"Audio Books"},"categoryTreeNodeLevel":2,"leafCategoryTreeNode":true,"parentCategoryTreeNodeHref":"https:\/\/api.sandbox.ebay.com\/commerce\/taxonomy\/v1\/category_tree\/15\/get_category_subtree?category_id=267"},{"category":{"categoryId":"45110","categoryName":"Accessories, Gift Books"},"categoryTreeNodeLevel":2,"childCategoryTreeNodes":[{"category":{"categoryId":"32044","categoryName":"Gift Books, Cards"},"categoryTreeNodeLevel":3,"leafCategoryTreeNode":true,"parentCategoryTreeNodeHref":"https:\/\/api.sandbox.ebay.com\/commerce\/taxonomy\/v1\/category_tree\/15\/get_category_subtree?category_id=45110"},{"category":{"categoryId":"45111","categoryName":"Address Books"},"categoryTreeNodeLevel":3,"leafCategoryTreeNode":true,"parentCategoryTreeNodeHref":"https:\/\/api.sandbox.ebay.com\/commerce\/taxonomy\/v1\/category_tree\/15\/get_category_subtree?category_id=45110"},{"category":{"categoryId":"45112","categoryName":"Diaries, Journals"},"categoryTreeNodeLevel":3,"leafCategoryTreeNode":true,"parentCategoryTreeNodeHref":"https:\/\/api.sandbox.ebay.com\/commerce\/taxonomy\/v1\/category_tree\/15\/get_category_subtree?category_id=45110"},{"category":{"categoryId":"45114","categoryName":"Bookmarks"},"categoryTreeNodeLevel":3,"leafCategoryTreeNode":true,"parentCategoryTreeNodeHref":"https:\/\/api.sandbox.ebay.com\/commerce\/taxonomy\/v1\/category_tree\/15\/get_category_subtree?category_id=45110"},{"category":{"categoryId":"45115","categoryName":"Other Accessories"},"categoryTreeNodeLevel":3,"leafCategoryTreeNode":true,"parentCategoryTreeNodeHref":"https:\/\/api.sandbox.ebay.com\/commerce\/taxonomy\/v1\/category_tree\/15\/get_category_subtree?category_id=45110"},{"category":{"categoryId":"120869","categoryName":"Reading Lights"},"categoryTreeNodeLevel":3,"leafCategoryTreeNode":true,"parentCategoryTreeNodeHref":"https:\/\/api.sandbox.ebay.com\/commerce\/taxonomy\/v1\/category_tree\/15\/get_category_subtree?category_id=45110"},{"category":{"categoryId":"156486","categoryName":"Calendars (current)"},"categoryTreeNodeLevel":3,"leafCategoryTreeNode":true,"parentCategoryTreeNodeHref":"https:\/\/api.sandbox.ebay.com\/commerce\/taxonomy\/v1\/category_tree\/15\/get_category_subtree?category_id=45110"}],"parentCategoryTreeNodeHref":"https:\/\/api.sandbox.ebay.com\/commerce\/taxonomy\/v1\/category_tree\/15\/get_category_subtree?category_id=267"},{"category":{"categoryId":"52543","categoryName":"Magazines"},"categoryTreeNodeLevel":2,"leafCategoryTreeNode":true,"parentCategoryTreeNodeHref":"https:\/\/api.sandbox.ebay.com\/commerce\/taxonomy\/v1\/category_tree\/15\/get_category_subtree?category_id=267"},{"category":{"categoryId":"171228","categoryName":"Fiction Books"},"categoryTreeNodeLevel":2,"leafCategoryTreeNode":true,"parentCategoryTreeNodeHref":"https:\/\/api.sandbox.ebay.com\/commerce\/taxonomy\/v1\/category_tree\/15\/get_category_subtree?category_id=267"},{"category":{"categoryId":"171243","categoryName":"Non-Fiction Books"},"categoryTreeNodeLevel":2,"leafCategoryTreeNode":true,"parentCategoryTreeNodeHref":"https:\/\/api.sandbox.ebay.com\/commerce\/taxonomy\/v1\/category_tree\/15\/get_category_subtree?category_id=267"},{"category":{"categoryId":"171273","categoryName":"Dictionaries & Reference"},"categoryTreeNodeLevel":2,"childCategoryTreeNodes":[{"category":{"categoryId":"91158","categoryName":"Atlases"},"categoryTreeNodeLevel":3,"leafCategoryTreeNode":true,"parentCategoryTreeNodeHref":"https:\/\/api.sandbox.ebay.com\/commerce\/taxonomy\/v1\/category_tree\/15\/get_category_subtree?category_id=171273"},{"category":{"categoryId":"125957","categoryName":"Street Directories"},"categoryTreeNodeLevel":3,"leafCategoryTreeNode":true,"parentCategoryTreeNodeHref":"https:\/\/api.sandbox.ebay.com\/commerce\/taxonomy\/v1\/category_tree\/15\/get_category_subtree?category_id=171273"},{"category":{"categoryId":"170610","categoryName":"Dictionaries"},"categoryTreeNodeLevel":3,"leafCategoryTreeNode":true,"parentCategoryTreeNodeHref":"https:\/\/api.sandbox.ebay.com\/commerce\/taxonomy\/v1\/category_tree\/15\/get_category_subtree?category_id=171273"},{"category":{"categoryId":"171274","categoryName":"Encyclopedias"},"categoryTreeNodeLevel":3,"leafCategoryTreeNode":true,"parentCategoryTreeNodeHref":"https:\/\/api.sandbox.ebay.com\/commerce\/taxonomy\/v1\/category_tree\/15\/get_category_subtree?category_id=171273"},{"category":{"categoryId":"171306","categoryName":"Thesauruses"},"categoryTreeNodeLevel":3,"leafCategoryTreeNode":true,"parentCategoryTreeNodeHref":"https:\/\/api.sandbox.ebay.com\/commerce\/taxonomy\/v1\/category_tree\/15\/get_category_subtree?category_id=171273"},{"category":{"categoryId":"171308","categoryName":"Other"},"categoryTreeNodeLevel":3,"leafCategoryTreeNode":true,"parentCategoryTreeNodeHref":"https:\/\/api.sandbox.ebay.com\/commerce\/taxonomy\/v1\/category_tree\/15\/get_category_subtree?category_id=171273"}],"parentCategoryTreeNodeHref":"https:\/\/api.sandbox.ebay.com\/commerce\/taxonomy\/v1\/category_tree\/15\/get_category_subtree?category_id=267"},{"category":{"categoryId":"171355","categoryName":"Books On Disc"},"categoryTreeNodeLevel":2,"leafCategoryTreeNode":true,"parentCategoryTreeNodeHref":"https:\/\/api.sandbox.ebay.com\/commerce\/taxonomy\/v1\/category_tree\/15\/get_category_subtree?category_id=267"},{"category":{"categoryId":"171488","categoryName":"Travel Guides"},"categoryTreeNodeLevel":2,"leafCategoryTreeNode":true,"parentCategoryTreeNodeHref":"https:\/\/api.sandbox.ebay.com\/commerce\/taxonomy\/v1\/category_tree\/15\/get_category_subtree?category_id=267"},{"category":{"categoryId":"171491","categoryName":"Graphic Novels"},"categoryTreeNodeLevel":2,"leafCategoryTreeNode":true,"parentCategoryTreeNodeHref":"https:\/\/api.sandbox.ebay.com\/commerce\/taxonomy\/v1\/category_tree\/15\/get_category_subtree?category_id=267"},{"category":{"categoryId":"171985","categoryName":"Magazine Subscriptions"},"categoryTreeNodeLevel":2,"leafCategoryTreeNode":true,"parentCategoryTreeNodeHref":"https:\/\/api.sandbox.ebay.com\/commerce\/taxonomy\/v1\/category_tree\/15\/get_category_subtree?category_id=267"},{"category":{"categoryId":"182882","categoryName":"Children & Young Adults Books"},"categoryTreeNodeLevel":2,"childCategoryTreeNodes":[{"category":{"categoryId":"279","categoryName":"Other Children & Young Adults"},"categoryTreeNodeLevel":3,"leafCategoryTreeNode":true,"parentCategoryTreeNodeHref":"https:\/\/api.sandbox.ebay.com\/commerce\/taxonomy\/v1\/category_tree\/15\/get_category_subtree?category_id=182882"},{"category":{"categoryId":"171210","categoryName":"Children & YA Non-Fiction"},"categoryTreeNodeLevel":3,"leafCategoryTreeNode":true,"parentCategoryTreeNodeHref":"https:\/\/api.sandbox.ebay.com\/commerce\/taxonomy\/v1\/category_tree\/15\/get_category_subtree?category_id=182882"},{"category":{"categoryId":"171220","categoryName":"Children's Fiction"},"categoryTreeNodeLevel":3,"leafCategoryTreeNode":true,"parentCategoryTreeNodeHref":"https:\/\/api.sandbox.ebay.com\/commerce\/taxonomy\/v1\/category_tree\/15\/get_category_subtree?category_id=182882"},{"category":{"categoryId":"171222","categoryName":"Young Adult Fiction"},"categoryTreeNodeLevel":3,"leafCategoryTreeNode":true,"parentCategoryTreeNodeHref":"https:\/\/api.sandbox.ebay.com\/commerce\/taxonomy\/v1\/category_tree\/15\/get_category_subtree?category_id=182882"},{"category":{"categoryId":"171276","categoryName":"Children's Picture Books"},"categoryTreeNodeLevel":3,"leafCategoryTreeNode":true,"parentCategoryTreeNodeHref":"https:\/\/api.sandbox.ebay.com\/commerce\/taxonomy\/v1\/category_tree\/15\/get_category_subtree?category_id=182882"}],"parentCategoryTreeNodeHref":"https:\/\/api.sandbox.ebay.com\/commerce\/taxonomy\/v1\/category_tree\/15\/get_category_subtree?category_id=267"}],"parentCategoryTreeNodeHref":"https:\/\/api.sandbox.ebay.com\/commerce\/taxonomy\/v1\/category_tree\/15\/get_category_subtree?category_id=0"}}